pipeless_ai_cli/__init__.py
pipeless_ai_cli/commands/__init__.py
pipeless_ai_cli/commands/create.py
pipeless_ai_cli/commands/install.py
pipeless_ai_cli/commands/list.py
pipeless_ai_cli/commands/run.py
pipeless_ai_cli/commands/templates/default/README.md
pipeless_ai_cli/commands/templates/default/app.py
pipeless_ai_cli/lib/pip.py
pipeless_ai_cli/lib/plugins.py
pipeless_ai_cli/main.py
pipeless_ai_cli/plugins-registry.json
pipeless_ai_cli-0.1.16.dist-info/LICENSE
pipeless_ai_cli-0.1.16.dist-info/METADATA
pipeless_ai_cli-0.1.16.dist-info/WHEEL
pipeless_ai_cli-0.1.16.dist-info/entry_points.txt
pipeless_ai_cli-0.1.16.dist-info/RECORD
