Metadata-Version: 2.1
Name: pipeless-ai-cli
Version: 0.1.16
Summary: An open-source computer vision framework to create and deploy computer vision applications that scale in minutes
Home-page: https://pipeless.ai
License: Apache-2.0
Keywords: multimedia,framework,artificial-intelligence,pipeline,developer-tools,computer-vision,image-processing
Author: Miguel Angel Cabrera Minagorri
Author-email: devgorri@gmail.com
Requires-Python: >=3.10,<4.0
Classifier: License :: OSI Approved :: Apache Software License
Classifier: Programming Language :: Python :: 3
Classifier: Programming Language :: Python :: 3.10
Classifier: Programming Language :: Python :: 3.11
Requires-Dist: gitpython (>=3.1.35,<4.0.0)
Requires-Dist: packaging (>=23.1,<24.0)
Requires-Dist: pipeless-ai (>=0.1.0,<0.2.0)
Requires-Dist: pyyaml (>=6.0.1,<7.0.0)
Requires-Dist: typer[all] (>=0.9.0,<0.10.0)
Project-URL: Documentation, https://github.com/pipeless-ai/pipeless
Project-URL: Repository, https://github.com/pipeless-ai/pipeless
